{
    "configurations": [
        {
            "browse": {
                "databaseFilename": "",
                "limitSymbolsToIncludedHeaders": true
            },
            "includePath": [
                "/opt/ros/melodic/include/**",
                "/home/mady/MEGA/mady/courses/learn_ros_python/simulation_ws/src/custom_robotic_arm/include/**",
                "/usr/include/**"
            ],
            "name": "ROS",
            "intelliSenseMode": "gcc-x64",
            "compilerPath": "/usr/bin/gcc",
            "cStandard": "c11",
            "cppStandard": "c++17"
        }
    ],
    "version": 4
}